inseq/__init__.py
inseq/attr/__init__.py
inseq/attr/attribution_decorators.py
inseq/attr/step_functions.py
inseq/attr/feat/__init__.py
inseq/attr/feat/attribution_utils.py
inseq/attr/feat/feature_attribution.py
inseq/attr/feat/gradient_attribution.py
inseq/attr/feat/internals_attribution.py
inseq/attr/feat/perturbation_attribution.py
inseq/attr/feat/ops/__init__.py
inseq/attr/feat/ops/discretized_integrated_gradients.py
inseq/attr/feat/ops/lime.py
inseq/attr/feat/ops/monotonic_path_builder.py
inseq/attr/feat/ops/reagent.py
inseq/attr/feat/ops/sequential_integrated_gradients.py
inseq/attr/feat/ops/value_zeroing.py
inseq/attr/feat/ops/reagent_core/__init__.py
inseq/attr/feat/ops/reagent_core/importance_score_evaluator.py
inseq/attr/feat/ops/reagent_core/rationalizer.py
inseq/attr/feat/ops/reagent_core/stopping_condition_evaluator.py
inseq/attr/feat/ops/reagent_core/token_replacer.py
inseq/attr/feat/ops/reagent_core/token_sampler.py
inseq/commands/__init__.py
inseq/commands/base.py
inseq/commands/cli.py
inseq/commands/commands_utils.py
inseq/commands/attribute/__init__.py
inseq/commands/attribute/attribute.py
inseq/commands/attribute/attribute_args.py
inseq/commands/attribute_context/__init__.py
inseq/commands/attribute_context/attribute_context.py
inseq/commands/attribute_context/attribute_context_args.py
inseq/commands/attribute_context/attribute_context_helpers.py
inseq/commands/attribute_context/attribute_context_viz_helpers.py
inseq/commands/attribute_dataset/__init__.py
inseq/commands/attribute_dataset/attribute_dataset.py
inseq/commands/attribute_dataset/attribute_dataset_args.py
inseq/data/__init__.py
inseq/data/aggregation_functions.py
inseq/data/aggregator.py
inseq/data/attribution.py
inseq/data/batch.py
inseq/data/data_utils.py
inseq/data/viz.py
inseq/models/__init__.py
inseq/models/attribution_model.py
inseq/models/decoder_only.py
inseq/models/encoder_decoder.py
inseq/models/huggingface_model.py
inseq/models/model_config.py
inseq/models/model_config.yaml
inseq-0.6.0.dist-info/LICENSE
inseq-0.6.0.dist-info/METADATA
inseq-0.6.0.dist-info/WHEEL
inseq-0.6.0.dist-info/entry_points.txt
inseq-0.6.0.dist-info/top_level.txt
inseq-0.6.0.dist-info/RECORD
