Metadata-Version: 2.1
Name: inseq
Version: 0.6.0
Summary: Interpretability for Sequence Generation Models 🔍
Author: The Inseq Team
Author-email: info@inseq.org
Maintainer: Gabriele Sarti
Maintainer-email: gabriele.sarti996@gmail.com
License: Apache License
Project-URL: homepage, https://github.com/inseq-team/inseq
Project-URL: documentation, https://inseq.org
Project-URL: repository, https://github.com/inseq-team/inseq
Project-URL: changelog, https://github.com/inseq-team/inseq/blob/main/CHANGELOG.md
Keywords: generative AI,transformers,natural language processing,XAI,explainable ai,interpretability,feature attribution,machine translation
Classifier: Development Status :: 3 - Alpha
Classifier: Environment :: Console
Classifier: Environment :: GPU
Classifier: Environment :: GPU :: NVIDIA CUDA
Classifier: Framework :: Jupyter
Classifier: Intended Audience :: Developers
Classifier: Intended Audience :: Science/Research
Classifier: License :: OSI Approved :: Apache Software License
Classifier: Operating System :: OS Independent
Classifier: Programming Language :: Python
Classifier: Programming Language :: Python :: 3
Classifier: Programming Language :: Python :: 3.9
Classifier: Programming Language :: Python :: 3.10
Classifier: Programming Language :: Python :: 3.11
Classifier: Topic :: Scientific/Engineering :: Artificial Intelligence
Classifier: Topic :: Scientific/Engineering :: Visualization
Classifier: Typing :: Typed
Requires-Python: >=3.9
License-File: LICENSE
Requires-Dist: rich >=10.13.0
Requires-Dist: transformers[sentencepiece,tokenizers] >=4.22.0
Requires-Dist: protobuf >=3.20.1
Requires-Dist: captum >=0.7.0
Requires-Dist: numpy >=1.21.6
Requires-Dist: jaxtyping >=0.2.25
Requires-Dist: typeguard <=2.13.3
Requires-Dist: torch >=2.1.1
Requires-Dist: matplotlib >=3.5.3
Requires-Dist: tqdm >=4.64.0
Requires-Dist: nvidia-cublas-cu11 >=11.10.3.66 ; sys_platform == "Linux"
Requires-Dist: nvidia-cuda-cupti-cu11 >=11.7.101 ; sys_platform == "Linux"
Requires-Dist: nvidia-cuda-nvrtc-cu11 >=11.7.99 ; sys_platform == "Linux"
Requires-Dist: nvidia-cuda-runtime-cu11 >=11.7.99 ; sys_platform == "Linux"
Requires-Dist: nvidia-cudnn-cu11 >=8.5.0.96 ; sys_platform == "Linux"
Requires-Dist: nvidia-cufft-cu11 >=10.9.0.58 ; sys_platform == "Linux"
Requires-Dist: nvidia-curand-cu11 >=10.2.10.91 ; sys_platform == "Linux"
Requires-Dist: nvidia-cusolver-cu11 >=11.4.0.1 ; sys_platform == "Linux"
Requires-Dist: nvidia-cusparse-cu11 >=11.7.4.91 ; sys_platform == "Linux"
Requires-Dist: nvidia-nccl-cu11 >=2.14.3 ; sys_platform == "Linux"
Requires-Dist: nvidia-nvtx-cu11 >=11.7.91 ; sys_platform == "Linux"
Provides-Extra: datasets
Requires-Dist: datasets >=2.17.0 ; extra == 'datasets'
Provides-Extra: docs
Requires-Dist: sphinx >=5.3.0 ; extra == 'docs'
Requires-Dist: sphinxemoji >=0.2.0 ; extra == 'docs'
Requires-Dist: sphinxext-opengraph >=0.4.2 ; extra == 'docs'
Requires-Dist: sphinx-copybutton >=0.4.0 ; extra == 'docs'
Requires-Dist: sphinx-gitstamp >=0.3.2 ; extra == 'docs'
Requires-Dist: sphinx-design >=0.4.1 ; extra == 'docs'
Requires-Dist: furo >=2022.12.7 ; extra == 'docs'
Provides-Extra: lint
Requires-Dist: bandit >=1.7.4 ; extra == 'lint'
Requires-Dist: safety >=3.1.0 ; extra == 'lint'
Requires-Dist: pydoclint >=0.4.0 ; extra == 'lint'
Requires-Dist: pre-commit >=2.19.0 ; extra == 'lint'
Requires-Dist: pytest >=7.2.0 ; extra == 'lint'
Requires-Dist: pytest-cov >=4.0.0 ; extra == 'lint'
Requires-Dist: pytest-xdist >=3.5.0 ; extra == 'lint'
Requires-Dist: ruff >=0.2.0 ; extra == 'lint'
Provides-Extra: nltk
Requires-Dist: nltk >=3.8.1 ; extra == 'nltk'
Provides-Extra: notebook
Requires-Dist: ipykernel >=6.29.2 ; extra == 'notebook'
Requires-Dist: ipywidgets >=8.1.2 ; extra == 'notebook'
Provides-Extra: sklearn
Requires-Dist: scikit-learn >=1.4.0 ; extra == 'sklearn'
Requires-Dist: joblib >=1.3.2 ; extra == 'sklearn'
